geomorphproject1/__init__.py
geomorphproject1/common.py
geomorphproject1/folium_map.py
geomorphproject1/geomorphproject1.py
geomorphproject1/ipyleaflet_map.py
geomorphproject1/ipyleaflet_map_lab8.py
geomorphproject1/leaflet_map.py
geomorphproject1/myfoliumap.py
geomorphproject1-0.0.5.dist-info/licenses/LICENSE
geomorphproject1-0.0.5.dist-info/METADATA
geomorphproject1-0.0.5.dist-info/WHEEL
geomorphproject1-0.0.5.dist-info/entry_points.txt
geomorphproject1-0.0.5.dist-info/top_level.txt
geomorphproject1-0.0.5.dist-info/RECORD
